{
  "clickhouse_cluster": {
    "node_count": 4,
    "node_cpus": 2.0,
    "node_ram_gb": 2.0,
    "cpus": 8.0,
    "ram_limit": "8g"
  },
  "scenario_config": {
    "duration_per_instance_sec": 30.0,
    "insert_batch_size_list": [
      1000,
      2000,
      3000,
      5000,
      8000,
      10000,
      15000,
      20000,
      30000,
      40000,
      50000,
      75000,
      100000
    ],
    "writer_thread_list": [
      1,
      2,
      3,
      4,
      5
    ],
    "reader_threads": 10,
    "max_retries": 3,
    "insert_request_timeout_seconds": 10.0,
    "read_request_timeout_seconds": 20.0
  },
  "warmup": {
    "enabled": true,
    "duration_seconds": 15
  }
}